colipy/__init__.py
colipy/example.py
colipy_cli-0.1.1.dev1.dist-info/LICENSE.txt
colipy_cli-0.1.1.dev1.dist-info/WHEEL
colipy_cli-0.1.1.dev1.dist-info/METADATA
colipy_cli-0.1.1.dev1.dist-info/RECORD
