Metadata-Version: 2.1
Name: colipy-cli
Version: 0.1.1.dev1
Summary: Colipy is a command line ui library for python.
Home-page: https://github.com/johannes-luebke/colipy
License: GPL-3.0-or-later
Author: Johannes Lübke
Author-email: 60359335+johannes-luebke@users.noreply.github.com
Requires-Python: >=3.10,<4.0
Classifier: Development Status :: 3 - Alpha
Classifier: Environment :: Console
Classifier: Intended Audience :: Developers
Classifier: License :: OSI Approved :: GNU General Public License v3 or later (GPLv3+)
Classifier: Programming Language :: Python :: 3
Classifier: Programming Language :: Python :: 3.10
Classifier: Programming Language :: Python :: 3.11
Project-URL: Repository, https://github.com/johannes-luebke/colipy
